COPYING
MANIFEST.in
README
health_nursing_report.xml
health_nursing_view.xml
setup.py
./__init__.py
./health_nursing.py
./health_nursing_report.xml
./health_nursing_view.xml
./tryton.cfg
./data/health_nursing_sequences.xml
./doc/index.rst
./icons/gnuhealth_nurse.svg
./locale/ar.po
./locale/de.po
./locale/el.po
./locale/es.po
./locale/fr.po
./locale/it_IT.po
./locale/ja_JP.po
./locale/lo.po
./locale/pt_BR.po
./locale/zh_CN.po
./report/round_report.odt
./security/access_rights.xml
./tests/__init__.py
./tests/test_health_nursing.py
./view/gnuhealth_ambulatory_care.xml
./view/gnuhealth_ambulatory_procedure_tree.xml
./view/gnuhealth_patient_ambulatory_care.xml
./view/gnuhealth_patient_ambulatory_care_tree.xml
./view/gnuhealth_patient_rounding.xml
./view/gnuhealth_patient_rounding_tree.xml
./view/gnuhealth_procedure_tree.xml
./view/gnuhealth_rounding_procedure.xml
data/health_nursing_sequences.xml
icons/README
icons/gnuhealth_nurse.svg
locale/ar.po
locale/de.po
locale/el.po
locale/es.po
locale/fr.po
locale/it_IT.po
locale/ja_JP.po
locale/lo.po
locale/pt_BR.po
locale/zh_CN.po
report/round_report.odt
security/access_rights.xml
trytond_health_nursing.egg-info/PKG-INFO
trytond_health_nursing.egg-info/SOURCES.txt
trytond_health_nursing.egg-info/dependency_links.txt
trytond_health_nursing.egg-info/entry_points.txt
trytond_health_nursing.egg-info/not-zip-safe
trytond_health_nursing.egg-info/requires.txt
trytond_health_nursing.egg-info/top_level.txt
view/gnuhealth_ambulatory_care.xml
view/gnuhealth_ambulatory_procedure_tree.xml
view/gnuhealth_patient_ambulatory_care.xml
view/gnuhealth_patient_ambulatory_care_tree.xml
view/gnuhealth_patient_rounding.xml
view/gnuhealth_patient_rounding_tree.xml
view/gnuhealth_procedure_tree.xml
view/gnuhealth_rounding_procedure.xml